MiniMem/__init__.py
minimem-0.0.1.dist-info/METADATA
minimem-0.0.1.dist-info/WHEEL
minimem-0.0.1.dist-info/top_level.txt
minimem-0.0.1.dist-info/RECORD
