Metadata-Version: 2.4
Name: minimem
Version: 0.0.1
Summary: Mini Memory.
Requires-Python: >=3.8
